AUTHORS
LICENSE
MANIFEST.in
README.rst
requirements.txt
setup.cfg
setup.py
openslides_csv_export/__init__.py
openslides_csv_export/apps.py
openslides_csv_export/urls.py
openslides_csv_export/views.py
openslides_csv_export.egg-info/PKG-INFO
openslides_csv_export.egg-info/SOURCES.txt
openslides_csv_export.egg-info/dependency_links.txt
openslides_csv_export.egg-info/entry_points.txt
openslides_csv_export.egg-info/requires.txt
openslides_csv_export.egg-info/top_level.txt
openslides_csv_export/static/js/openslides_csv_export/base.js
openslides_csv_export/static/js/openslides_csv_export/site.js
openslides_csv_export/static/templates/openslides_csv_export/overview.html