Metadata-Version: 1.1
Name: openslides-csv-export
Version: 2.0.4
Summary: OpenSlides CSV Export Plugin
Home-page: https://github.com/OpenSlides/openslides-csv-export
Author: Authors of OpenSlides CSV Export Plugin, see AUTHORS
Author-email: support@openslides.org
License: MIT
Keywords: OpenSlides
Platform: UNKNOWN
Classifier: Development Status :: 5 - Production/Stable
Classifier: Environment :: Plugins
Classifier: Environment :: Web Environment
Classifier: Framework :: Django
Classifier: License :: OSI Approved :: MIT License
Classifier: Operating System :: OS Independent
Classifier: Programming Language :: Python :: 3.5
Classifier: Programming Language :: Python :: 3.6
Classifier: Programming Language :: Python :: 3.7
